setup.py
rpi_feature_selection_toolbox/__init__.py
rpi_feature_selection_toolbox/rpi_feature_selection_toolbox.ctf
rpi_feature_selection_toolbox.egg-info/PKG-INFO
rpi_feature_selection_toolbox.egg-info/SOURCES.txt
rpi_feature_selection_toolbox.egg-info/dependency_links.txt
rpi_feature_selection_toolbox.egg-info/requires.txt
rpi_feature_selection_toolbox.egg-info/top_level.txt