Metadata-Version: 1.0
Name: rpi-feature-selection-toolbox
Version: 2.1.2
Summary: RPI primitives using the latest 2018.4.18 APIs
Home-page: https://www.ecse.rpi.edu/~cvrl/
Author: Keyi Liu, Zijun Cui, Qiang Ji
Author-email: UNKNOWN
License: UNKNOWN
Platform: Linux
Platform: MacOS
